pkuwsl/__init__.py
pkuwsl/code_test.py
pkuwsl-1.3.dist-info/METADATA
pkuwsl-1.3.dist-info/WHEEL
pkuwsl-1.3.dist-info/top_level.txt
pkuwsl-1.3.dist-info/RECORD
