Metadata-Version: 2.1
Name: pkuwsl
Version: 1.3
Summary: 吃枣药丸
Home-page: https://zhuanlan.zhihu.com/p/26159930
Author: yellowjilin
Author-email: yellowjilin@gmail.com
License: UNKNOWN
Platform: UNKNOWN
